machine/__init__.py
micropython/__init__.py
network/__init__.py
ucollections/__init__.py
umqtt/__init__.py
umqtt/simple.py
utime/__init__.py
micropython_teststubs_sebastian_stigler-0.0.4.dist-info/LICENSE
micropython_teststubs_sebastian_stigler-0.0.4.dist-info/METADATA
micropython_teststubs_sebastian_stigler-0.0.4.dist-info/WHEEL
micropython_teststubs_sebastian_stigler-0.0.4.dist-info/top_level.txt
micropython_teststubs_sebastian_stigler-0.0.4.dist-info/RECORD
